<?xml version="1.0" encoding="utf-8" ?>
<dwsync>
<file name="flash-logo.png" server="www3.nccu.edu.tw" local="129665399400000000" remote="129680123400000000" />
<file name="quicktime-logo.gif" server="www3.nccu.edu.tw" local="129665399400000000" remote="129693013800000000" />
<file name="t_1.jpg" server="www3.nccu.edu.tw" local="129665399400000000" remote="129680123400000000" />
<file name="t_2.jpg" server="www3.nccu.edu.tw" local="129665399400000000" remote="129680123400000000" />
<file name="t_3.jpg" server="www3.nccu.edu.tw" local="129665399400000000" remote="129680123400000000" />
<file name="t_4.jpg" server="www3.nccu.edu.tw" local="129665399400000000" remote="129680123400000000" />
<file name="t_5.jpg" server="www3.nccu.edu.tw" local="129665399400000000" remote="129680123400000000" />
<file name="t_6.jpg" server="www3.nccu.edu.tw" local="129665399400000000" remote="129680123400000000" />
<file name="t_7.jpg" server="www3.nccu.edu.tw" local="129665399400000000" remote="129680123400000000" />
<file name="t_8.jpg" server="www3.nccu.edu.tw" local="129665399400000000" remote="129680123400000000" />
<file name="t_9.jpg" server="www3.nccu.edu.tw" local="129665400000000000" remote="129680123400000000" />
<file name="t_post.jpg" server="www3.nccu.edu.tw" local="129665400000000000" remote="129693013800000000" />
<file name="t_postr.jpg" server="www3.nccu.edu.tw" local="129665400000000000" remote="129693013800000000" />
</dwsync>